LICENSE.txt
README.md
setup.py
two_pcepd/__init__.py
two_pcepd/model.py
two_pcepd.egg-info/PKG-INFO
two_pcepd.egg-info/SOURCES.txt
two_pcepd.egg-info/dependency_links.txt
two_pcepd.egg-info/requires.txt
two_pcepd.egg-info/top_level.txt