Metadata-Version: 2.1
Name: two-pcepd
Version: 0.1.5
Summary: The official implementation of the 2pCePd-Net model. pBPf Fusion block coming soon...
Author: Supratim Ghosh, Sourav Pramanik, Anoop Kumar Tiwari, Kottakkaran Sooppy Nisar, Mahantapas Kundu, Mita Nasipuri
Author-email: supratimghosh2772@gmail.com
License: GNU General Public License v3.0
Platform: UNKNOWN
Classifier: Programming Language :: Python :: 3.9
License-File: LICENSE.txt
